{
  "embedding_files": [
    "gt_30.0s_f485.jpg",
    "gt_24.7s_f370.jpg",
    "gt_18.7s_f246.jpg",
    "gt_23.3s_f339.jpg",
    "gt_28.7s_f456.jpg"
  ],
  "backup_files": [
    "gt_29.3s_f473.jpg",
    "gt_27.3s_f429.jpg",
    "gt_21.3s_f299.jpg",
    "gt_26.7s_f415.jpg",
    "gt_28.0s_f444.jpg"
  ],
  "scores": {
    "gt_30.0s_f485.jpg": 24.6439,
    "gt_24.7s_f370.jpg": 23.1977,
    "gt_18.7s_f246.jpg": 23.0642,
    "gt_23.3s_f339.jpg": 22.5872,
    "gt_28.7s_f456.jpg": 22.3317,
    "gt_29.3s_f473.jpg": 21.9499,
    "gt_27.3s_f429.jpg": 21.7923,
    "gt_21.3s_f299.jpg": 21.737,
    "gt_26.7s_f415.jpg": 21.6872,
    "gt_28.0s_f444.jpg": 21.6628
  }
}